README.rst
setup.py
nivision/__init__.py
nivision/camera.py
nivision/core.py
nivision/gdiplus.py
nivision/private.py
nivision/version.py
pynivision.egg-info/PKG-INFO
pynivision.egg-info/SOURCES.txt
pynivision.egg-info/dependency_links.txt
pynivision.egg-info/top_level.txt