Metadata-Version: 1.0
Name: pynivision
Version: 2015.0.0
Summary: Python Wrappers for NI Vision and IMAQdx
Home-page: https://github.com/robotpy/pynivision
Author: Peter Johnson
Author-email: robotpy@googlegroups.com
License: BSD
Keywords: frc first robotics wpilib nivision imaqdx vision imaq
Platform: UNKNOWN
